django_fanout.py
setup.cfg
setup.py
django_fanout.egg-info/PKG-INFO
django_fanout.egg-info/SOURCES.txt
django_fanout.egg-info/dependency_links.txt
django_fanout.egg-info/requires.txt
django_fanout.egg-info/top_level.txt