Metadata-Version: 1.1
Name: django-fanout
Version: 1.1.0
Summary: Fanout.io library for Django
Home-page: https://github.com/fanout/django-fanout
Author: Justin Karneges
Author-email: justin@fanout.io
License: MIT
Platform: UNKNOWN
Classifier: Topic :: Utilities
Classifier: License :: OSI Approved :: MIT License
